pytexutils/__init__.py
pytexutils/figures/__init__.py
pytexutils/figures/image.py
pytexutils/figures/tabular_image.py
pytexutils/graphs/__init__.py
pytexutils/graphs/bar_chart.py
pytexutils/graphs/line_chart.py
pytexutils/graphs/pie_chart.py
pytexutils/gui/__init__.py
pytexutils/gui/table_editor.py
pytexutils/tables/__init__.py
pytexutils/tables/table.py
pytexutils/utils/__init__.py
pytexutils/utils/writer.py
tests/__init__.py
tests/test_bar_chart.py
tests/test_figure.py
tests/test_line_chart.py
tests/test_pie_chart.py
tests/test_table.py
tests/test_table_editor.py
tests/test_writer.py
pytexutils-0.1.19.dist-info/LICENSE
pytexutils-0.1.19.dist-info/METADATA
pytexutils-0.1.19.dist-info/WHEEL
pytexutils-0.1.19.dist-info/top_level.txt
pytexutils-0.1.19.dist-info/RECORD
