Metadata-Version: 2.1
Name: pytexutils
Version: 0.1.19
Summary: Python LaTeX Utils.
Home-page: https://github.com/alessandrosebastianelli/latex-utils.git
Author: Alessandro Sebastianelli
Author-email: Alessandro Sebastianelli <alessandro.sebastianelli1995@gmail.com>
License: Copyright (c) 2023-2023 Alessandro Sebastianelli        
Project-URL: Homepage, https://github.com/alessandrosebastianelli/latex-utils
Project-URL: Bug Tracker, https://github.com/alessandrosebastianelli/latex-utils/issues
Classifier: Programming Language :: Python :: 3
Classifier: License :: OSI Approved :: MIT License
Classifier: Operating System :: OS Independent
Requires-Python: >=3.7
License-File: LICENSE
Requires-Dist: numpy
